app/__init__.py
app/config.py
app/rapid_email.py
app/adapters/common_adapters.py
test_2_rapid_email-2.0.dist-info/METADATA
test_2_rapid_email-2.0.dist-info/WHEEL
test_2_rapid_email-2.0.dist-info/top_level.txt
test_2_rapid_email-2.0.dist-info/RECORD
