Metadata-Version: 2.1
Name: test-2-rapid-email
Version: 2.0
Summary: Sending email notification.
Author: Abhishek Negi
